{
  "id": "huggingface__strands-lerobot-hub-to-hardware",
  "slug": "strands-lerobot-hub-to-hardware",
  "source": "huggingface",
  "url": "https://huggingface.co/blog/amazon/strands-lerobot-hub-to-hardware",
  "category": "News",
  "date": "2026-06-17T10:18:05.000Z",
  "image": null,
  "title": {
    "en": "From the Hugging Face Hub to robot hardware with Strands Agents and LeRobot",
    "th": "ตั้งแต่ Hugging Face Hub ไปจนถึงฮาร์ดแวร์หุ่นยนต์ด้วย Strands Agents และ LeRobot"
  },
  "summary": {
    "en": "From the Hugging Face Hub to robot hardware with Strands Agents and LeRobot",
    "th": "ตั้งแต่ Hugging Face Hub ไปจนถึงฮาร์ดแวร์หุ่นยนต์ด้วย Strands Agents และ LeRobot"
  },
  "body": [
    {
      "type": "p",
      "text": {
        "en": "From the Hugging Face Hub to robot hardware with Strands Agents and LeRobot",
        "th": "ตั้งแต่ Hugging Face Hub ไปจนถึงฮาร์ดแวร์หุ่นยนต์ด้วย Strands Agents และ LeRobot"
      }
    }
  ]
}
